local_data_platform/__init__.py
local_data_platform/catalog/__init__.py
local_data_platform/catalog/sql.py
local_data_platform/catalog.py
local_data_platform/download.py
local_data_platform/entity_class.py
local_data_platform/hello_world.py
local_data_platform/pipelines/__init__.py
local_data_platform/pipelines/python/__init__.py
local_data_platform/pipelines/python/base_pipeline.py
local_data_platform/pipelines/python/ingestion/__init__.py
local_data_platform/pipelines/python/ingestion/create_table.py
local_data_platform/source/__init__.py
local_data_platform/source/base_source.py
local_data_platform/source/parquet/__init__.py
local_data_platform/source/parquet/read.py
local_data_platform/tmp/warehouse/pyiceberg_catalog.db
local_data_platform-0.1.0.dist-info/METADATA
local_data_platform-0.1.0.dist-info/WHEEL
local_data_platform-0.1.0.dist-info/RECORD
